dio_img_processing/__init__.py
dio_img_processing/processing/__init__.py
dio_img_processing/processing/combination.py
dio_img_processing/processing/transformation.py
dio_img_processing/utils/__init__.py
dio_img_processing/utils/io.py
dio_img_processing/utils/plot.py
dio_img_processing-0.0.2.dist-info/METADATA
dio_img_processing-0.0.2.dist-info/WHEEL
dio_img_processing-0.0.2.dist-info/top_level.txt
dio_img_processing-0.0.2.dist-info/RECORD
