Metadata-Version: 2.1
Name: dio-img-processing
Version: 0.0.2
Summary: Image processing tool.
Home-page: https://github.com/jgr-araujo/dio-img-processing
Author: Josimar Gabriel R. de Araújo
Author-email: jgr-araujo@protonmail.com
License: UNKNOWN
Platform: UNKNOWN
Requires-Python: >=3.8
